<?xml version="1.0" encoding="utf-8"?>
<song xmlns="http://21wdh.staszic.waw.pl" xmlns:xsi="http://www.w3.org/2001/XMLSchema-instance" xsi:schemaLocation="http://21wdh.staszic.waw.pl Song.xsd" title="Hiszpanka z Callao">
  <alias/>
  <text_author type="solo">Henryk Czekała; Sławomir Klupś</text_author>
  <comment>Fragmenty tekstą są cytatami z Edwarda Stachury</comment>
  <composer type="solo">Tradycyjna</composer>
  <artist type="band">Mechanicy Shanty</artist>
  <translator/>
  <original_title/>
  <lyric>
    <block type="verse">
      <row important_over="false"><ch a="G"/>Przepuściłem znów całą forsę swą<ch a="e"/></row>
      <row important_over="false"><ch a="C"/>Na hiszpańską dziewkę z Callao<ch a="D"/></row>
      <row important_over="false"><ch a="G"/>Wyciągnęła ze mnie cały szmal<ch a="e"/></row>
      <row important_over="false"><ch a="C"/>I spłukałem na nią się do cna<ch a="D"/></row>
    </block>
    <block type="verse">
      <row important_over="false"><ch a="G"/>Już znikają główki portu<ch a="e"/></row>
      <row important_over="false"><ch a="C"/>W którym stary został dom<ch a="D"/></row>
      <row important_over="false"><ch a="G"/>Znów za rufą niknie w dali<ch a="e"/></row>
      <row important_over="false"><ch a="C"/>Ukochany stały ląd<ch a="D"/></row>
    </block>
    <block type="chorus">
      <row important_over="false"><ch a="G"/>Dalej chłopcy rwijmy fały<ch a="e"/></row>
      <row important_over="false"><ch a="C"/>Niech uderzy w żagle wiatr<ch a="D"/></row>
      <row important_over="false"><ch a="G"/>W morze znów wypływamy<ch a="e"/></row>
      <row important_over="false"><ch a="C"/>Ile tam spędzimy lat<ch a="D"/></row>
    </block>
    <block type="verse">
      <row important_over="false"><ch a="G"/>Już niejeden pokład mym domem był<ch a="e"/></row>
      <row important_over="false"><ch a="C"/>I niejeden bat me plecy bił<ch a="D"/></row>
      <row important_over="false"><ch a="G"/>Choć robota ciężka i żarcie psie<ch a="e"/></row>
      <row important_over="false"><ch a="C"/>W Callao po rejsie znajdziesz mnie<ch a="D"/></row>
    </block>
    <blocklink blocknb="2"/>
    <blocklink blocknb="3"/>
    <block type="verse">
      <row important_over="false"><ch a="G"/>Zaprószyłem tam nieraz głowę swą<ch a="e"/></row>
      <row important_over="false"><ch a="C"/>W barze u Hiszpanki z Callao<ch a="D"/></row>
      <row important_over="false"><ch a="G"/>Butlę rumu wielką dała mi<ch a="e"/></row>
      <row important_over="false"><ch a="C"/>I ciągnęła ze mną aż po świt<ch a="D"/></row>
    </block>
    <blocklink blocknb="2"/>
    <blocklink blocknb="3"/>
    <block type="verse">
      <row important_over="false"><ch a="G"/>A pod Cape Horn gdzie nas poniesie wiatr<ch a="e"/></row>
      <row important_over="false"><ch a="C"/>Popłyniemy z sztormem za pan brat<ch a="D"/></row>
      <row important_over="false"><ch a="G"/>Przez groźne burze śnieg i lód<ch a="e"/></row>
      <row important_over="false"><ch a="C"/>Dojdziemy aż do piekła wrót<ch a="D"/></row>
    </block>
    <block type="verse">
      <row important_over="false"><ch a="G"/>Choć zgarbieją z zimna ręce<ch a="e"/></row>
      <row important_over="false"><ch a="C"/>Zadek mokry dzień i noc<ch a="D"/></row>
      <row important_over="false"><ch a="G"/>Jedna myśl rozgrzewa serce<ch a="e"/></row>
      <row important_over="false"><ch a="C"/>O Hiszpance z Callao<ch a="D"/></row>
    </block>
    <blocklink blocknb="3"/>
  </lyric>
  <music metre="">
    <guitar barre="0"/>
  </music>
  <status>
    <verificators/>
    <to_do/>
  </status>
</song>
